commify/__init__.py
commify/apikeymanager.py
commify/git.py
commify/main.py
commify/utils.py
commify/version.py
commify-1.9.dist-info/licenses/LICENSE
commify-1.9.dist-info/METADATA
commify-1.9.dist-info/WHEEL
commify-1.9.dist-info/entry_points.txt
commify-1.9.dist-info/top_level.txt
commify-1.9.dist-info/RECORD
