Metadata-Version: 2.4
Name: Commify
Version: 1.9
Summary: Commify: You Should Commit Yourself.
Home-page: https://matuco19.com/Commify
Author: Matuco19
License: MATCO-Open-Source
Project-URL: Source Code, https://github.com/Matuco19/Commify
Project-URL: Bug Tracker, https://github.com/Matuco19/Commify/issues
Keywords: commify,python,ai,commit,commits,git,github,gpt,language-model,automation,commits,gpt-4,gpt4,gpt-4o,gpt4o,gpt4-o,gpt-4omni,o1,o3-mini,o3,o4-mini,o4,deepseek-r1,gemini-2.5-flash,gemini-2.5-pro,gemini-2.0-flash,groq,cli,cli-app,ollama,ollama-api,llama3,llama3.1,llama3.2,llama3.3,matuco19,openai,python3,gitpython,pollinations.ai,pollinations,google-generativeai,gemini,gemini-api,google-ai
License-File: LICENSE
Requires-Dist: ollama
Requires-Dist: GitPython
Requires-Dist: g4f
Requires-Dist: rich
Requires-Dist: requests
Requires-Dist: openai
Requires-Dist: groq
Requires-Dist: google-generativeai
Dynamic: author
Dynamic: description
Dynamic: description-content-type
Dynamic: home-page
Dynamic: keywords
Dynamic: license
Dynamic: license-file
Dynamic: project-url
Dynamic: requires-dist
Dynamic: summary
